{"Operation":"SubmitProbes","Payload":"[{\"icon-small\":17303451,\"invalid_charger\":0,\"level\":76,\"GUID\":\"029c5ce9-8960-4575-ae45-7125ebc608df\",\"health\":2,\"scale\":100,\"PRIORITY\":false,\"technology\":\"Li-poly\",\"charge_counter\":219295,\"max_charging_current\":0,\"PROBE_TRANSMIT_MODE\":0,\"voltage\":4029,\"TIMESTAMP\":1553281452,\"temperature\":362,\"max_charging_voltage\":0,\"present\":true,\"battery_low\":false,\"PROBE\":\"edu.northwestern.cbits.purple_robot_manager.probes.builtin.BatteryProbe\",\"plugged\":0,\"seq\":46185,\"status\":3},{\"icon-small\":17303451,\"invalid_charger\":0,\"level\":70,\"GUID\":\"b230d196-08a5-488d-aebe-df9fb995f936\",\"health\":2,\"scale\":100,\"PRIORITY\":false,\"technology\":\"Li-poly\",\"charge_counter\":201910,\"max_charging_current\":0,\"PROBE_TRANSMIT_MODE\":0,\"voltage\":3989,\"TIMESTAMP\":1553284733,\"temperature\":347,\"max_charging_voltage\":0,\"present\":true,\"battery_low\":false,\"PROBE\":\"edu.northwestern.cbits.purple_robot_manager.probes.builtin.BatteryProbe\",\"plugged\":0,\"seq\":46221,\"status\":3},{\"CALL_STATE\":\"Idle\",\"TIMESTAMP\":1553284735,\"GUID\":\"a9764a4c-4fe5-4ecc-ad36-9acc3ba3bb53\",\"PROBE_TRANSMIT_MODE\":0,\"PROBE\":\"edu.northwestern.cbits.purple_robot_manager.probes.builtin.CallStateProbe\"},{\"DAY_OF_YEAR\":82,\"MONTH\":3,\"DST_OFFSET\":0,\"DAY_OF_MONTH\":23,\"WEEK_OF_MONTH\":4,\"GUID\":\"4f38cb90-8df7-4ce1-ad03-25f1d09005d9\",\"PROBE_TRANSMIT_MODE\":0,\"DAY_OF_WEEK_IN_MONTH\":4,\"WEEK_OF_YEAR\":12,\"HOUR_OF_DAY\":1,\"TIMESTAMP\":1553283105,\"MINUTE\":1,\"DAY_OF_WEEK\":7,\"PROBE\":\"edu.northwestern.cbits.purple_robot_manager.probes.builtin.DateCalendarProbe\"},{\"BOARD\":\"msm8953\",\"GUID\":\"994ddc2c-e2ad-44eb-9423-fc0169828763\",\"DEVICE\":\"tissot_sprout\",\"BLUETOOTH_MAC\":\"02:00:00:00:00:00\",\"HOST\":\"mi-server\",\"MODEL\":\"Mi A1\",\"MANUFACTURER\":\"Xiaomi\",\"PROBE_TRANSMIT_MODE\":0,\"BRAND\":\"xiaomi\",\"DISPLAY\":\"PKQ1.180917.001.V10.0.4.0.PDHMIXM\",\"WIFI_MAC\":\"02:00:00:00:00:00\",\"FINGERPRINT\":\"xiaomi\\\/tissot\\\/tissot_sprout:9\\\/PKQ1.180917.001\\\/V10.0.4.0.PDHMIXM:user\\\/release-keys\",\"HARDWARE\":\"qcom\",\"PRODUCT\":\"tissot\",\"TIMESTAMP\":1553283105,\"MOBILE_ID\":\"867707033071764\",\"BOOTLOADER\":\"MSM8953_TISSOT2.0_20190104174247\",\"ID\":\"PKQ1.180917.001\",\"PROBE\":\"edu.northwestern.cbits.purple_robot_manager.probes.builtin.HardwareInformationProbe\"},{\"TIME_FIX\":1553282799536,\"TIMESTAMP\":1553283105,\"LONGITUDE\":78.3456743,\"PROVIDER\":\"network\",\"GUID\":\"72e7869d-9abf-44f5-970a-8fbf7b6c9956\",\"NETWORK_AVAILABLE\":true,\"PROBE_TRANSMIT_MODE\":0,\"LATITUDE\":17.4454469,\"PROBE\":\"edu.northwestern.cbits.purple_robot_manager.probes.builtin.LocationProbe\",\"ACCURACY\":24.009000778198242,\"GPS_AVAILABLE\":true},{\"psc\":-1,\"IS_FORWARDING\":false,\"GUID\":\"cf8ee44d-f06a-43e9-8d9c-59d1eead5a33\",\"GSM_ERROR_RATE\":0,\"HAS_ICC_CARD\":true,\"PROBE_TRANSMIT_MODE\":0,\"SIM_OPERATOR_NAME\":\"JIO\",\"lac\":126,\"SIM_COUNTRY_ISO\":\"in\",\"CALL_STATE\":0,\"NETWORK_TYPE\":\"GSM\",\"SIM_STATE\":\"Ready\",\"NETWORK_COUNTRY_ISO\":\"in\",\"GSM_SIGNAL_STRENGTH\":0,\"TIMESTAMP\":1553283105,\"SERVICE_STATE\":\"In Service\",\"DEVICE_SOFTWARE_VERSION\":\"00\",\"NETWORK_OPERATOR\":\"405854\",\"PHONE_TYPE\":\"GSM\",\"PROBE\":\"edu.northwestern.cbits.purple_robot_manager.probes.builtin.TelephonyProbe\",\"cid\":2212122},{\"BRIGHT_COUNT\":0,\"DIM_LOCKS\":[],\"PARTIAL_COUNT\":0,\"TIMESTAMP\":1553283105,\"GUID\":\"a46d7e5a-8714-49b6-b6b2-45784f488208\",\"FULL_LOCKS\":[],\"BRIGHT_LOCKS\":[],\"PARTIAL_LOCKS\":[],\"DIM_COUNT\":0,\"PROBE_TRANSMIT_MODE\":0,\"PROBE\":\"edu.northwestern.cbits.purple_robot_manager.probes.builtin.WakeLockInformationProbe\",\"FULL_COUNT\":0},{\"SUNSET\":1553345400559,\"TIMESTAMP\":1553283105,\"LONGITUDE\":78.3456743,\"SUNRISE\":1553299020559,\"IS_DAY\":false,\"SUNRISE_DISTANCE\":-15915000,\"GUID\":\"24f72b5b-2147-462f-a0e9-70bd031eb473\",\"SUNSET_DISTANCE\":-62295000,\"PROBE_TRANSMIT_MODE\":0,\"LATITUDE\":17.4454469,\"PROBE\":\"edu.northwestern.cbits.purple_robot_manager.probes.features.SunriseSunsetFeature\",\"DAY_DURATION\":46380000},{\"INTERFACE_NAME\":\"wlan0\",\"INTERFACE_DISPLAY\":\"wlan0\",\"HOSTNAME\":\"10.42.0.233\",\"TIMESTAMP\":1553283105,\"GUID\":\"a1fe4283-97e2-41f4-9232-2633b8933f00\",\"IP_ADDRESS\":\"10.42.0.233\",\"PROBE_TRANSMIT_MODE\":0,\"PROBE\":\"edu.northwestern.cbits.purple_robot_manager.probes.builtin.NetworkProbe\"},{\"CURRENT_RSSI\":-23,\"ACCESS_POINTS\":[{\"BSSID\":\"9c:4e:36:4e:6f:70\",\"CAPABILITIES\":\"[WPA2-PSK-CCMP][ESS][WPS]\",\"FREQUENCY\":2412,\"LEVEL\":-23,\"SSID\":\"ubuntu-Lenovo-U410\"},{\"BSSID\":\"f8:94:c2:24:54:7d\",\"CAPABILITIES\":\"[WPA2-PSK-CCMP][ESS][WPS]\",\"FREQUENCY\":2412,\"LEVEL\":-53,\"SSID\":\"chitta-FX503VD\"},{\"BSSID\":\"34:23:87:c0:0e:ed\",\"CAPABILITIES\":\"[WPA2-PSK-CCMP+TKIP][WPA-PSK-CCMP+TKIP][ESS][WPS]\",\"FREQUENCY\":2412,\"LEVEL\":-68,\"SSID\":\"crusher\"},{\"BSSID\":\"c0:38:96:37:76:bd\",\"CAPABILITIES\":\"[WPA2-PSK-CCMP][ESS][WPS]\",\"FREQUENCY\":2412,\"LEVEL\":-75,\"SSID\":\"MyPC\"},{\"BSSID\":\"6c:72:20:f2:09:33\",\"CAPABILITIES\":\"[WPA-PSK-CCMP][WPA2-PSK-CCMP][ESS]\",\"FREQUENCY\":2457,\"LEVEL\":-77,\"SSID\":\"NoWifiForYou\"},{\"BSSID\":\"b8:27:eb:92:08:a9\",\"CAPABILITIES\":\"[WPA2-PSK-CCMP][ESS]\",\"FREQUENCY\":2442,\"LEVEL\":-79,\"SSID\":\"wifi@home\"},{\"BSSID\":\"44:94:fc:5a:db:1c\",\"CAPABILITIES\":\"[WPA2-PSK-CCMP][ESS][WPS]\",\"FREQUENCY\":2462,\"LEVEL\":-80,\"SSID\":\"Robust\"},{\"BSSID\":\"78:0c:b8:70:93:ab\",\"CAPABILITIES\":\"[WPA2-PSK-CCMP+TKIP][WPA-PSK-CCMP+TKIP][ESS][WPS]\",\"FREQUENCY\":2412,\"LEVEL\":-84,\"SSID\":\"Wifi\"},{\"BSSID\":\"c4:e9:84:c6:16:ac\",\"CAPABILITIES\":\"[WPA2-PSK-CCMP][ESS]\",\"FREQUENCY\":2462,\"LEVEL\":-88,\"SSID\":\"Hello\"},{\"BSSID\":\"80:a5:89:8c:78:67\",\"CAPABILITIES\":\"[WPA2-PSK-CCMP+TKIP][WPA-PSK-CCMP+TKIP][ESS][WPS]\",\"FREQUENCY\":2412,\"LEVEL\":-91,\"SSID\":\"vpatare-pc\"},{\"BSSID\":\"50:64:2b:ce:ae:a2\",\"CAPABILITIES\":\"[WPA-PSK-TKIP+CCMP][WPA2-PSK-TKIP+CCMP][ESS][WPS]\",\"FREQUENCY\":2462,\"LEVEL\":-91,\"SSID\":\"Mywifi\"},{\"BSSID\":\"00:db:df:78:f5:1e\",\"CAPABILITIES\":\"[WPA2-PSK-CCMP+TKIP][WPA-PSK-CCMP+TKIP][ESS][WPS]\",\"FREQUENCY\":2412,\"LEVEL\":-95,\"SSID\":\"jarvis\"}],\"TIMESTAMP\":1553283106,\"GUID\":\"2ad2f3f1-d74f-4799-a705-5ddf7b343998\",\"CURRENT_BSSID\":\"9c:4e:36:4e:6f:70\",\"ACCESS_POINT_COUNT\":12,\"PROBE_TRANSMIT_MODE\":0,\"PROBE\":\"edu.northwestern.cbits.purple_robot_manager.probes.builtin.WifiAccessPointsProbe\",\"CURRENT_LINK_SPEED\":72,\"CURRENT_SSID\":\"\\\"ubuntu-Lenovo-U410\\\"\"},{\"TIME_FIX\":1553283106950,\"TIMESTAMP\":1553283107,\"LONGITUDE\":78.3456689,\"PROVIDER\":\"network\",\"GUID\":\"fc3242cd-104f-486d-b5c5-441b1b12e2fe\",\"NETWORK_AVAILABLE\":true,\"PROBE_TRANSMIT_MODE\":0,\"LATITUDE\":17.4454366,\"PROBE\":\"edu.northwestern.cbits.purple_robot_manager.probes.builtin.LocationProbe\",\"ACCURACY\":24.1299991607666,\"GPS_AVAILABLE\":true},{\"SUNSET\":1553345400087,\"TIMESTAMP\":1553283107,\"LONGITUDE\":78.3456689,\"SUNRISE\":1553299020087,\"IS_DAY\":false,\"SUNRISE_DISTANCE\":-15913000,\"GUID\":\"16ca50d1-af8c-425e-800c-1f95ba64bfe3\",\"SUNSET_DISTANCE\":-62293000,\"PROBE_TRANSMIT_MODE\":0,\"LATITUDE\":17.4454366,\"PROBE\":\"edu.northwestern.cbits.purple_robot_manager.probes.features.SunriseSunsetFeature\",\"DAY_DURATION\":46380000}]","UserHash":"34237272481aa6a02ea94799695a6982","Checksum":"60636c2ea91b3760337de4d2f67d7f75","ContentLength":6678}